djsciops/__init__.py
djsciops/authentication.py
djsciops/command_line.py
djsciops/log.py
djsciops/settings.py
djsciops/utils.py
djsciops/version.py
djsciops/axon/__init__.py
djsciops/axon/speed_audit.py
djsciops/axon_gui/__init__.py
djsciops/axon_gui/icon.ico
djsciops/axon_gui/main.py
djsciops/axon_gui/main.ui
djsciops/axon_gui/resources.qrc
djsciops/axon_gui/images/icons/cil-3d.png
djsciops/axon_gui/images/icons/cil-4k.png
djsciops/axon_gui/images/icons/cil-account-logout.png
djsciops/axon_gui/images/icons/cil-action-redo.png
djsciops/axon_gui/images/icons/cil-action-undo.png
djsciops/axon_gui/images/icons/cil-airplane-mode-off.png
djsciops/axon_gui/images/icons/cil-airplane-mode.png
djsciops/axon_gui/images/icons/cil-alarm.png
djsciops/axon_gui/images/icons/cil-align-center.png
djsciops/axon_gui/images/icons/cil-align-left.png
djsciops/axon_gui/images/icons/cil-align-right.png
djsciops/axon_gui/images/icons/cil-arrow-bottom-2.png
djsciops/axon_gui/images/icons/cil-arrow-bottom.png
djsciops/axon_gui/images/icons/cil-arrow-circle-bottom.png
djsciops/axon_gui/images/icons/cil-arrow-circle-left.png
djsciops/axon_gui/images/icons/cil-arrow-circle-right.png
djsciops/axon_gui/images/icons/cil-arrow-circle-top.png
djsciops/axon_gui/images/icons/cil-arrow-left.png
djsciops/axon_gui/images/icons/cil-arrow-right.png
djsciops/axon_gui/images/icons/cil-arrow-top.png
djsciops/axon_gui/images/icons/cil-at.png
djsciops/axon_gui/images/icons/cil-av-timer.png
djsciops/axon_gui/images/icons/cil-ban.png
djsciops/axon_gui/images/icons/cil-battery-0.png
djsciops/axon_gui/images/icons/cil-battery-3.png
djsciops/axon_gui/images/icons/cil-battery-5.png
djsciops/axon_gui/images/icons/cil-battery-alert.png
djsciops/axon_gui/images/icons/cil-battery-slash.png
djsciops/axon_gui/images/icons/cil-bell.png
djsciops/axon_gui/images/icons/cil-bluetooth.png
djsciops/axon_gui/images/icons/cil-briefcase.png
djsciops/axon_gui/images/icons/cil-browser.png
djsciops-1.5.9.dist-info/METADATA
djsciops-1.5.9.dist-info/WHEEL
djsciops-1.5.9.dist-info/entry_points.txt
djsciops-1.5.9.dist-info/top_level.txt
djsciops-1.5.9.dist-info/RECORD
