Metadata-Version: 2.1
Name: djsciops
Version: 1.5.9
Summary: A suite of customer CLI tools for DataJoint SciOps.
Home-page: https://github.com/dj-sciops/djsciops-python
Author: DataJoint
Author-email: djbot@datajoint.io
Classifier: Programming Language :: Python :: 3
Classifier: License :: OSI Approved :: MIT License
Classifier: Operating System :: OS Independent
Requires-Python: ~=3.8
Requires-Dist: boto3
Requires-Dist: tqdm
Requires-Dist: appdirs
Requires-Dist: flask>=2.3.2
Requires-Dist: pyyaml
Requires-Dist: pyside6
Requires-Dist: pillow
Requires-Dist: botocore
Requires-Dist: packaging
Requires-Dist: speedtest-cli
Requires-Dist: minio
